{
    "タイトル": "大山WP　異常報告書",
    "速報": {
        "件名": "空検出口ボトル凹み",
        "発生日": "2017/03/06",
        "ライン": "Aライン",
        "発生アラーム名": "-",
        "アラームTAG": "-",
        "工程": "容器製造",
        "設備": "空瓶　検査・内圧ﾘｰｸ検査機",
        "ユニット": "出口搬送",
        "部位": "出口スター",
        "部品名": "出口スターポケット",
        "調合・製品液欠減": "無し",
        "廃棄金額": "-千円",
        "4M変更起因": "NO",
        "生産品目": "MWD2F",
        "停止種別": "生産中停止",
        "生産ｽﾀｰﾄ": "3月6日18時51分",
        "停止時間": 21,
        "品質異常": "有り",
        "工程状況連絡書": "無し",
        "部品交換": "無し",
        "原料欠減": "無し",
        "4M変更登録管理No": "-"
    },
	"停止時間": 21,
	"発生日": "2017-03-06",
    "報告サークル": "すいせき",
    "報告者": "宿野　大志",
    "現象": "充填出口で、凹みボトルが確認された。空瓶検査機を確認したところ、出口スター部分でボトルが凹む音が確認された。"
}